{"id":"86727502","premium":false,"billing_type":{"id":"standard","name":"Стандарт"},"relations":[],"name":"Сварщик на полуавтомат","insider_interview":null,"response_letter_required":false,"area":{"id":"2","name":"Санкт-Петербург","url":"https://api.hh.ru/areas/2?host=hh.ru"},"salary":{"from":110000,"to":null,"currency":"RUR","gross":false},"type":{"id":"open","name":"Открытая"},"address":null,"allow_messages":true,"experience":{"id":"between1And3","name":"От 1 года до 3 лет"},"schedule":{"id":"fullDay","name":"Полный день"},"employment":{"id":"full","name":"Полная занятость"},"department":null,"contacts":null,"description":"<p><strong>Предоставляется отсрочка в соответствии с п. 9 указа</strong></p> <p><strong>ООО «Кингисеппский машиностроительный завод» - крупнейший отечественный завод- изготовитель дизельного, теплообменного и палубного оборудования, компрессоров высокого давления, осуществляющий все виды ремонта и обслуживания дизельных и газотурбинных двигателей, генераторов и редукторов. Предприятие является надёжным поставщиком и исполнителем, хорошо зарекомендовавший себя по итогам выполнения ряда государственных контрактов.</strong></p> <p><strong>Обязанности:</strong></p> <ul> <li>Работа полуавтоматической сваркой;</li> <li>Заготовка и сборка металлоконструкций;</li> <li>Чтение чертежей.</li> </ul> <strong>Требования:</strong> <ul> <li>Опыт работы в подготовке и сварке металлоконструкций;</li> <li>Уверенное владение сваркой;</li> <li>Удостоверение сварщика. Если нет специального образования, но имеется опыт, то мы ждём вас на собеседовании!</li> <li>Умение читать чертежи;</li> </ul> <strong>Условия:</strong> <ul> <li>Оформление по ТК РФ с первого дня;</li> <li>График работы 5/2 (возможность обговорить график с руководством при собеседовании);</li> <li>Полная официальная зарплата без задержек;</li> <li>Возможность повышения квалификации без отрыва от производства;</li> <li>На современных производственных площадках: теплые цеха, отличная столовая, вкуснейшие обеды;</li> <li>Возможность работы вахтовым методом;</li> <li><strong>Итоговый уровень заработной платы обсуждается на собеседовании с руководителем в зависимости от квалификации;</strong></li> <li>Возможность приема на работу иностранных граждан (при необходимости оформим документы для квалифицированных специалистов);</li> <li>Возможность повышения квалификации;</li> <li>Отзывчивое руководство, отличный коллектив;</li> <li>Для нас нет понятий о возрасте;</li> </ul> <p><strong><em>«КМЗ – МЫ ЗАБОТИМСЯ О КОЛЛЕКТИВЕ»</em></strong></p>","branded_description":null,"vacancy_constructor_template":null,"key_skills":[],"accept_handicapped":false,"accept_kids":false,"archived":false,"response_url":null,"specializations":[],"professional_roles":[{"id":"109","name":"Сварщик"}],"code":null,"hidden":false,"quick_responses_allowed":false,"driver_license_types":[],"accept_incomplete_resumes":true,"employer":{"id":"2505348","name":"Кингисеппский Машиностроительный завод","url":"https://api.hh.ru/employers/2505348?host=hh.ru","alternate_url":"https://hh.ru/employer/2505348","logo_urls":{"original":"https://img.hhcdn.ru/employer-logo-original/1147400.jpg","240":"https://img.hhcdn.ru/employer-logo/6210166.jpeg","90":"https://img.hhcdn.ru/employer-logo/6210165.jpeg"},"vacancies_url":"https://api.hh.ru/vacancies?employer_id=2505348&host=hh.ru","accredited_it_employer":false,"trusted":true},"published_at":"2024-03-01T17:08:50+0300","created_at":"2024-03-01T17:08:50+0300","initial_created_at":"2023-09-14T14:44:58+0300","negotiations_url":null,"suitable_resumes_url":null,"apply_alternate_url":"https://hh.ru/applicant/vacancy_response?vacancyId=86727502","has_test":false,"test":null,"alternate_url":"https://hh.ru/vacancy/86727502","working_days":[],"working_time_intervals":[],"working_time_modes":[],"accept_temporary":false,"languages":[],"approved":true}