{"id":"88298629","premium":false,"billing_type":{"id":"standard","name":"Стандарт"},"relations":[],"name":"Электрогазосварщик (сварщик на полуавтомат)","insider_interview":null,"response_letter_required":false,"area":{"id":"3","name":"Екатеринбург","url":"https://api.hh.ru/areas/3?host=hh.ru"},"salary":{"from":60000,"to":180000,"currency":"RUR","gross":false},"type":{"id":"open","name":"Открытая"},"address":{"city":"Екатеринбург","street":"проспект Космонавтов","building":"15П1","lat":56.872836,"lng":60.609377,"description":null,"raw":"Екатеринбург, проспект Космонавтов, 15П1","metro":{"station_name":"Машиностроителей","line_name":"Север-Юг","station_id":"48.263","line_id":"48","lat":56.878517,"lng":60.61218},"metro_stations":[{"station_name":"Машиностроителей","line_name":"Север-Юг","station_id":"48.263","line_id":"48","lat":56.878517,"lng":60.61218}]},"allow_messages":true,"experience":{"id":"between1And3","name":"От 1 года до 3 лет"},"schedule":{"id":"shift","name":"Сменный график"},"employment":{"id":"full","name":"Полная занятость"},"department":null,"contacts":null,"description":"<p><strong>Завод Резервуаров и Негабаритных Металлоконструкций</strong></p> <p>Наш завод входит в число предприятий России по производству и поставкам резервуаров, емкостей стальных и нержавеющих, сложного нестандартного оборудования для горно-металлургической отрасли</p> <p>Производственное подразделение нашей компании занимается <strong>проектированием и производством сварных емкостей, резервуаров тип РГС, РВС, ЗУМПФ по</strong> индивидуальным и типовым проектам.</p> <p>Мы постоянно <strong>совершенствуемся </strong>и находим <strong>новые пути развития в сфере промышленности</strong>!</p> <p>Для нас важен <strong>рост</strong> и<strong> развитие</strong> сотрудников, поэтому мы помогаем им раскрыть свой потенциал. Мы даем возможность <strong>для вертикального и горизонтального роста</strong>.</p> <p>В настоящее время ищем единомышленников, так как активно развиваемся и перед нами стоят <strong>амбициозные задачи.</strong></p> <p>Приглашаем в нашу команду<strong> Электрогазосварщика!</strong></p> <p><strong>Обязанности:</strong></p> <ul> <li> <p>Качественная сварка металлоконструкций, резервуаров <strong>(работа в бригаде со слесарем-сборщиком, обрубщиком);</strong></p> </li> <li>Чтение чертежей различной сложности деталей, узлов и конструкций.</li> </ul> <p><strong>Условия:</strong></p> <ul> <li>Официальное трудоустройство со всеми социальными гарантиями по ТК РФ;</li> <li>Своевременная выплата заработной платы (оклад + премия по результатам работы за месяц);</li> <li>График работы <strong>сменный 2/2 (с 08:00 до 20:00) либо 3/3;</strong></li> <li>Возможен выход на <strong>гибкий график;</strong></li> <li>Работа в теплом цехе;</li> <li>Обустроенная кухня, душевая;</li> <li>Район работы: г. Екатеринбург, ул. <strong>Космонавтов 15, лит. П1</strong> (в пешей доступности от м. Машиностроителей);</li> <li> <p><strong>БЕСПЛАТНОЕ</strong> проживание в комфортабельном общежитии в шаговой доступности от места работы иногородним + оплачиваем проезд до места собеседования;</p> </li> <li> <p><strong>БЕСПЛАТНОЕ </strong>прохождение медосмотра;</p> </li> <li> <p><strong>БЕСПЛАТНОЕ</strong> предоставление спецодежды и СИЗ;</p> </li> <li> <p><strong>Возможность выйти на сдельную оплата труда с 1-го дня;</strong></p> </li> <li> <p>Парковочное место, душевые кабины;</p> </li> <li> <p><strong>Есть возможность карьерного роста и развития</strong> до мастера, бригадира, начальника производства и т.д.</p> </li> </ul> <p><strong>Требования:</strong></p> <ul> <li> <p>Практический опыт работы не менее 1-го года;</p> </li> <li> <p>Опыт работы на сварке полуавтомат или аргонодуговая не менее 1-го года<strong>;</strong></p> </li> <li> <p>Сварка <strong>под проверку УЗК или давлением</strong> (сварка на герметичность);</p> </li> <li> <p>Умение читать конструкторскую документацию.</p> </li> </ul> <p> </p>","branded_description":null,"vacancy_constructor_template":null,"key_skills":[{"name":"Сварочные работы"},{"name":"Чтение чертежей"},{"name":"Слесарные работы"},{"name":"Сварка"},{"name":"Монтаж металлоконструкций"},{"name":"Производство строительно-монтажных работ"},{"name":"Сборочное производство"},{"name":"НАКС"},{"name":"Умение читать чертежи"},{"name":"Работа с чертежами"},{"name":"Работа с электроинструментом"},{"name":"Контроль качества"},{"name":"Точность и внимательность к деталям"},{"name":"Умение работать в коллективе"},{"name":"Аргонодуговая сварка"},{"name":"Полуавтоматическая сварка"},{"name":"Работа в команде"},{"name":"Цех"},{"name":"Работа в условиях многозадачности"}],"accept_handicapped":false,"accept_kids":false,"archived":false,"response_url":null,"specializations":[],"professional_roles":[{"id":"109","name":"Сварщик"}],"code":null,"hidden":false,"quick_responses_allowed":false,"driver_license_types":[],"accept_incomplete_resumes":false,"employer":{"id":"4935049","name":"Завод РиНМ","url":"https://api.hh.ru/employers/4935049?host=hh.ru","alternate_url":"https://hh.ru/employer/4935049","logo_urls":{"original":"https://img.hhcdn.ru/employer-logo-original/778795.png","240":"https://img.hhcdn.ru/employer-logo/3556072.png","90":"https://img.hhcdn.ru/employer-logo/3556071.png"},"vacancies_url":"https://api.hh.ru/vacancies?employer_id=4935049&host=hh.ru","accredited_it_employer":false,"trusted":true},"published_at":"2024-03-14T12:35:27+0300","created_at":"2024-03-14T12:35:27+0300","initial_created_at":"2023-10-17T15:52:21+0300","negotiations_url":null,"suitable_resumes_url":null,"apply_alternate_url":"https://hh.ru/applicant/vacancy_response?vacancyId=88298629","has_test":false,"test":null,"alternate_url":"https://hh.ru/vacancy/88298629","working_days":[],"working_time_intervals":[],"working_time_modes":[],"accept_temporary":true,"languages":[],"approved":true}