{"id":"93281934","premium":false,"billing_type":{"id":"standard","name":"Стандарт"},"relations":[],"name":"Сварщик","insider_interview":null,"response_letter_required":false,"area":{"id":"2","name":"Санкт-Петербург","url":"https://api.hh.ru/areas/2?host=hh.ru"},"salary":{"from":100000,"to":120000,"currency":"RUR","gross":true},"type":{"id":"open","name":"Открытая"},"address":{"city":null,"street":null,"building":null,"lat":null,"lng":null,"description":null,"raw":null,"metro":{"station_name":"Выборгская","line_name":"Кировско-Выборгская","station_id":"14.196","line_id":"14","lat":59.970925,"lng":30.347408},"metro_stations":[{"station_name":"Выборгская","line_name":"Кировско-Выборгская","station_id":"14.196","line_id":"14","lat":59.970925,"lng":30.347408},{"station_name":"Лесная","line_name":"Кировско-Выборгская","station_id":"14.195","line_id":"14","lat":59.984947,"lng":30.344259},{"station_name":"Площадь Ленина","line_name":"Кировско-Выборгская","station_id":"14.197","line_id":"14","lat":59.955611,"lng":30.35605}]},"allow_messages":true,"experience":{"id":"between3And6","name":"От 3 до 6 лет"},"schedule":{"id":"fullDay","name":"Полный день"},"employment":{"id":"full","name":"Полная занятость"},"department":null,"contacts":null,"description":"<strong>Обязанности:</strong> <ul> <li>Проведение сварочных работ различного назначения</li> <li>Сварка нержавейки, алюминия, стальных металлоконструкций</li> <li>Ответственное отношение к работе</li> <li>Умение пользоваться мерительным инструментом.</li> </ul> <strong>Требования:</strong> <ul> <li>Ответственность</li> <li>Опыт работ Tig, Mig.</li> <li>Умение читать чертежи</li> <li>Уверенное (подтвержденное) владение сварочными системами и аппаратами.</li> </ul> <strong>Условия:</strong> <ul> <li>График работы 5/2, возможно организовать сменный график</li> <li>Оформление по ТК, месячный испытательный срок</li> <li>Оплата труда + премии + переработки</li> <li>В шаговой доступности метро Выборгская, метро Площадь Ленина</li> <li>Иногородним предоставления жилья.</li> </ul>","branded_description":null,"vacancy_constructor_template":null,"key_skills":[{"name":"Сварочные работы"},{"name":"Чтение чертежей"}],"accept_handicapped":false,"accept_kids":false,"archived":false,"response_url":null,"specializations":[],"professional_roles":[{"id":"109","name":"Сварщик"}],"code":null,"hidden":false,"quick_responses_allowed":false,"driver_license_types":[],"accept_incomplete_resumes":true,"employer":{"id":"10570919","name":"Консилен","url":"https://api.hh.ru/employers/10570919?host=hh.ru","alternate_url":"https://hh.ru/employer/10570919","logo_urls":{"original":"https://img.hhcdn.ru/employer-logo-original/1200253.png","90":"https://img.hhcdn.ru/employer-logo/6421461.png","240":"https://img.hhcdn.ru/employer-logo/6421462.png"},"vacancies_url":"https://api.hh.ru/vacancies?employer_id=10570919&host=hh.ru","accredited_it_employer":false,"trusted":true},"published_at":"2024-02-15T12:58:03+0300","created_at":"2024-02-15T12:58:03+0300","initial_created_at":"2024-02-15T12:58:03+0300","negotiations_url":null,"suitable_resumes_url":null,"apply_alternate_url":"https://hh.ru/applicant/vacancy_response?vacancyId=93281934","has_test":false,"test":null,"alternate_url":"https://hh.ru/vacancy/93281934","working_days":[],"working_time_intervals":[],"working_time_modes":[],"accept_temporary":false,"languages":[],"approved":true}