{"id":"93885085","premium":false,"billing_type":{"id":"standard","name":"Стандарт"},"relations":[],"name":"Сварщик","insider_interview":null,"response_letter_required":false,"area":{"id":"1635","name":"Зеленодольск (Республика Татарстан)","url":"https://api.hh.ru/areas/1635?host=hh.ru"},"salary":{"from":150000,"to":null,"currency":"RUR","gross":false},"type":{"id":"open","name":"Открытая"},"address":{"city":"Зеленодольск","street":null,"building":null,"lat":55.847048,"lng":48.492802,"description":null,"raw":"Зеленодольск","metro":null,"metro_stations":[]},"allow_messages":true,"experience":{"id":"between1And3","name":"От 1 года до 3 лет"},"schedule":{"id":"flyInFlyOut","name":"Вахтовый метод"},"employment":{"id":"full","name":"Полная занятость"},"department":null,"contacts":null,"description":"<p><strong><strong>ООО &quot;АльфаПроф&quot; осуществляет свою деятельность с 2021 года и является прямым работодателем, предоставляя работу вахтовым методом на крупных заводах России. В компании работают квалифицированные специалисты в модернизации и ремонту пассажирских вагонов, судостроении, а также литейного производства. Мы предлагаем актуальные вакансии в крупных города России (Тамбов, Зеленодольск, Тверь, Воронеж), с конкурирующей заработной платой на рынке, стабильной работой и комфортными условиями труда. Связь в WhatsApp;Telegram</strong></strong></p> <p>Приглашаем на работу вахтовым методом сварщик-аргонщик на крупное производство</p> <p>Обязанности:</p> <ul> <li>Ручная аргонодуговая сварка поверхностей разной сложности. Это могут быть: трубопроводы, различные конструкции и устройства.</li> <li>Изучение и чтение чертежей сварных металлоконструкций разной сложности.</li> <li>Наплавление деталей, узлов и инструментов.</li> <li>Строгание, резка и сварка сложных деталей, выполненных из различных сталей, металлов и сплавов.</li> </ul> <p>Требования:</p> <ul> <li>Опыт работы</li> <li>Умение читать чертежи</li> </ul> <p> Условия:</p> <ul> <li>Прямой работодатель</li> <li>Вахта 60/30</li> <li>График работы 6/1</li> <li>Почасовая оплата</li> <li>Тарифная ставка от 550-600руб/час от выработки</li> <li>Компенсация проезда</li> <li>Новая спец.одежда</li> <li>Предоставление бесплатного жилья на квартирах</li> <li>Оформление по ТК РФ</li> <li>Стабильные выплаты</li> <li>Аванс вновь прибывшим</li> <li>Возможно обучение для получения удостоверения квалификации, разряда</li> <li>г.Зеленодольск</li> <li>Заработная плата от 150000 рублей</li> </ul> <p> </p>","branded_description":null,"vacancy_constructor_template":null,"key_skills":[],"accept_handicapped":false,"accept_kids":false,"archived":false,"response_url":null,"specializations":[],"professional_roles":[{"id":"109","name":"Сварщик"}],"code":"code 5804861","hidden":false,"quick_responses_allowed":false,"driver_license_types":[],"accept_incomplete_resumes":true,"employer":{"id":"10356674","name":"АльфаПроф","url":"https://api.hh.ru/employers/10356674?host=hh.ru","alternate_url":"https://hh.ru/employer/10356674","logo_urls":{"90":"https://img.hhcdn.ru/employer-logo/6305366.jpeg","original":"https://img.hhcdn.ru/employer-logo-original/1171234.jpeg","240":"https://img.hhcdn.ru/employer-logo/6305367.jpeg"},"vacancies_url":"https://api.hh.ru/vacancies?employer_id=10356674&host=hh.ru","accredited_it_employer":false,"trusted":true},"published_at":"2024-02-27T16:22:49+0300","created_at":"2024-02-27T16:22:49+0300","initial_created_at":"2024-02-27T16:22:49+0300","negotiations_url":null,"suitable_resumes_url":null,"apply_alternate_url":"https://hh.ru/applicant/vacancy_response?vacancyId=93885085","has_test":false,"test":null,"alternate_url":"https://hh.ru/vacancy/93885085","working_days":[],"working_time_intervals":[],"working_time_modes":[],"accept_temporary":false,"languages":[],"approved":true}