{"id":"93921025","premium":false,"billing_type":{"id":"standard_plus","name":"Стандарт плюс"},"relations":[],"name":"Сварщик-аргонщик","insider_interview":null,"response_letter_required":false,"area":{"id":"2085","name":"Долгопрудный","url":"https://api.hh.ru/areas/2085?host=hh.ru"},"salary":{"from":80000,"to":150000,"currency":"RUR","gross":false},"type":{"id":"open","name":"Открытая"},"address":{"city":"деревня Грибки","street":"Ангарская улица","building":"8","lat":55.953971,"lng":37.561787,"description":null,"raw":"деревня Грибки, Ангарская улица, 8","metro":null,"metro_stations":[]},"allow_messages":true,"experience":{"id":"between1And3","name":"От 1 года до 3 лет"},"schedule":{"id":"fullDay","name":"Полный день"},"employment":{"id":"full","name":"Полная занятость"},"department":null,"contacts":null,"description":"<p>Наша компания специализируется на оказании услуг по металлообработке и производстве корпусных изделий на заказ.</p> <p> </p> <p><strong>В связи с постоянным расширением производства компания СМАРТ СТИЛ приглашает на открытую вакансию сварщика</strong></p> <strong>Обязанности:</strong> <p>- Сварка металлических изделий</p> <strong>Требования:</strong> <p>- Среднее образование по специальности - Электрогазосварщик</p> <p>- Опыт работы от 3 лет</p> <p>- Умение читать чертежи, знание условных обозначений и гостов</p> <p>- Умение работать с инструментами</p> <p>- Умение самостоятельно собирать конструкции по чертежам</p> <p>- Владение аргонно-дуговой сваркой (сварка алюминия и его сплавов) будет являться преимуществом</p> <p>- Владение полуавтоматической сваркой</p> <p><strong>Условия:</strong></p> <p><strong>- </strong>Полная занятость 5/2</p> <p>- Официальное трудоустройство</p> <p>- Заработная плата 80 000 - 150 000 руб. в зависимости от квалификации и объема выполненных работ</p> <p>- Переработки оплачиваются</p> <p>- Возможность карьерного роста</p> <p>- Работа в Мытищинском районе, деревня Грибки, ул. Ангарская вл.8 стр.4 (рядом с г. Долгопрудный). 20 минут на автобусе от м. Алтуфьево или 7 минут от с. Долгопрудная</p>","branded_description":null,"vacancy_constructor_template":null,"key_skills":[{"name":"Работа в команде"},{"name":"Умение эффективно планировать свое время"},{"name":"Точность и внимательность"},{"name":"Умение работать в условиях многозадачности"},{"name":"Сварочные работы"}],"accept_handicapped":false,"accept_kids":false,"archived":false,"response_url":null,"specializations":[],"professional_roles":[{"id":"109","name":"Сварщик"}],"code":null,"hidden":false,"quick_responses_allowed":false,"driver_license_types":[],"accept_incomplete_resumes":false,"employer":{"id":"4162071","name":"Смарт стил","url":"https://api.hh.ru/employers/4162071?host=hh.ru","alternate_url":"https://hh.ru/employer/4162071","logo_urls":{"90":"https://img.hhcdn.ru/employer-logo/4274772.jpeg","240":"https://img.hhcdn.ru/employer-logo/4274773.jpeg","original":"https://img.hhcdn.ru/employer-logo-original/958561.jpeg"},"vacancies_url":"https://api.hh.ru/vacancies?employer_id=4162071&host=hh.ru","accredited_it_employer":false,"trusted":true},"published_at":"2024-03-14T10:49:25+0300","created_at":"2024-03-14T10:49:25+0300","initial_created_at":"2024-02-28T10:49:25+0300","negotiations_url":null,"suitable_resumes_url":null,"apply_alternate_url":"https://hh.ru/applicant/vacancy_response?vacancyId=93921025","has_test":false,"test":null,"alternate_url":"https://hh.ru/vacancy/93921025","working_days":[],"working_time_intervals":[],"working_time_modes":[],"accept_temporary":false,"languages":[],"approved":true}