{"id":"94321377","premium":false,"billing_type":{"id":"standard","name":"Стандарт"},"relations":[],"name":"Слесарь-сварщик","insider_interview":null,"response_letter_required":false,"area":{"id":"4","name":"Новосибирск","url":"https://api.hh.ru/areas/4?host=hh.ru"},"salary":{"from":75000,"to":85000,"currency":"RUR","gross":false},"type":{"id":"open","name":"Открытая"},"address":{"city":"Новосибирск","street":"Серебренниковская улица","building":"14","lat":55.020673,"lng":82.927383,"description":null,"raw":"Новосибирск, Серебренниковская улица, 14","metro":{"station_name":"Октябрьская","line_name":"Ленинская","station_id":"52.298","line_id":"52","lat":55.018789,"lng":82.939007},"metro_stations":[{"station_name":"Октябрьская","line_name":"Ленинская","station_id":"52.298","line_id":"52","lat":55.018789,"lng":82.939007},{"station_name":"Площадь Ленина","line_name":"Ленинская","station_id":"52.297","line_id":"52","lat":55.029941,"lng":82.92069},{"station_name":"Речной вокзал","line_name":"Ленинская","station_id":"52.299","line_id":"52","lat":55.008738,"lng":82.93827}]},"allow_messages":true,"experience":{"id":"between1And3","name":"От 1 года до 3 лет"},"schedule":{"id":"fullDay","name":"Полный день"},"employment":{"id":"full","name":"Полная занятость"},"department":null,"contacts":null,"description":"<p>Добрый день! Меня зовут Александр и я руковожу компанией по производству и продаже оборудования для косметологии (вакуумно-роликовые аппараты).</p> <p><strong>Наша компания Beautysib на рынке уже более 5 лет</strong> и является одним из лидеров в этой сфере. Мы поставляем оборудование по всей России и СНГ, <strong>а прирост компании составляет 30-50% в год.</strong></p> <p>Мы основываемся на собственных разработках (сейчас выпускаем уже третью линейку), и сейчас <strong>мы ждем в нашу команду сварщика.</strong></p> <p><strong>Обязанности:</strong></p> <ul> <li> <p>Чтение операционных технологических карт</p> </li> <li> <p>Проведение подготовительные работы перед сваркой</p> </li> <li> <p>Проверка и настройка оборудования, необходимого для работы</p> </li> <li> <p>Установка оптимальных режимов сварки</p> </li> <li> <p>Выполнение сварочных работы, прихватки элементов конструкции (сварка полуавтомат, иногда аргоном, иногда дугой в целях ускорения процесса)</p> </li> <li> <p>Устранение дефектов поверхности металла, появившиеся после выполнения сварочных работ, зачистка швов.</p> </li> <li> <p>Резка металла и некоторые виды слесарных работ</p> </li> <li> <p>Выполнение графиков сварочных работ</p> </li> <li> <p>Соблюдения правил ОТ и ПБ</p> </li> </ul> <p><strong>Требования:</strong></p> <ul> <li> <p>Среднее профессиональное образование, курсы подготовки и повышения квалификации.</p> </li> <li> <p>Знание сварочного оборудования, особенностей его настройки и эксплуатации или огромное желание научиться.</p> </li> <li> <p>Умение работать в режиме многозадачности и в команде.</p> </li> </ul> <p><strong>Условия:</strong></p> <ul> <li> <p>Стабильная заработная плата (на испытательный срок 75000, далее 85000), выплаты 2 раза в месяц, задержек не бывает</p> </li> <li> <p>График работы: 5/2 с 8.00 до 17.00 (+ 1 суббота в месяц рабочая, оплачивается отдельно).</p> </li> <li> <p>Оформление по ТК РФ.</p> </li> </ul>","branded_description":null,"vacancy_constructor_template":null,"key_skills":[{"name":"Сварочные работы"},{"name":"Слесарные работы"}],"accept_handicapped":false,"accept_kids":false,"archived":false,"response_url":null,"specializations":[],"professional_roles":[{"id":"109","name":"Сварщик"}],"code":null,"hidden":false,"quick_responses_allowed":false,"driver_license_types":[],"accept_incomplete_resumes":true,"employer":{"id":"3954904","name":"BeautySib","url":"https://api.hh.ru/employers/3954904?host=hh.ru","alternate_url":"https://hh.ru/employer/3954904","logo_urls":{"240":"https://img.hhcdn.ru/employer-logo/3723196.jpeg","90":"https://img.hhcdn.ru/employer-logo/3723195.jpeg","original":"https://img.hhcdn.ru/employer-logo-original/820577.jpg"},"vacancies_url":"https://api.hh.ru/vacancies?employer_id=3954904&host=hh.ru","accredited_it_employer":false,"trusted":true},"published_at":"2024-03-15T08:42:25+0300","created_at":"2024-03-15T08:42:25+0300","initial_created_at":"2024-03-06T10:27:19+0300","negotiations_url":null,"suitable_resumes_url":null,"apply_alternate_url":"https://hh.ru/applicant/vacancy_response?vacancyId=94321377","has_test":false,"test":null,"alternate_url":"https://hh.ru/vacancy/94321377","working_days":[],"working_time_intervals":[],"working_time_modes":[],"accept_temporary":false,"languages":[],"approved":true}