{"id":"94722129","premium":false,"billing_type":{"id":"standard_plus","name":"Стандарт плюс"},"relations":[],"name":"Сварщик","insider_interview":null,"response_letter_required":false,"area":{"id":"71","name":"Пенза","url":"https://api.hh.ru/areas/71?host=hh.ru"},"salary":{"from":70000,"to":80000,"currency":"RUR","gross":false},"type":{"id":"open","name":"Открытая"},"address":{"city":"Пенза","street":"улица Ленина","building":"6","lat":53.215559,"lng":45.006252,"description":null,"raw":"Пенза, улица Ленина, 6","metro":null,"metro_stations":[]},"allow_messages":true,"experience":{"id":"between1And3","name":"От 1 года до 3 лет"},"schedule":{"id":"fullDay","name":"Полный день"},"employment":{"id":"full","name":"Полная занятость"},"department":null,"contacts":null,"description":"<p><strong>Внимание! </strong>Производственная компания Sagarti, расположенная в г. Пенза, открывает <strong>КОНКУРС</strong> <strong>(до 31 марта)</strong> на позицию сварщика.</p> <p>Наше производство уникально, аналогов ему нет в России: ручной труд, используемые материалы.</p> <p><br />Команда бренда &quot;Sagarti&quot; - это коллектив, работающий на принципах взаимоуважения, поддержки, постоянного развития и творческого подхода.</p> <p><em><strong>Более 7 <em>лет</em> мы успешно поставляем продукцию для частных и общественных пространств в лучшие интерьеры по всему миру. На сегодняшний день география наших заказов – 23 страны. У компании есть представительство в Доха, Катар.</strong></em><br /><br />В производственном подразделении работают профессиональные и креативные специалисты, зарекомендовавшие свои имена как в России, так и за рубежом. Со стороны руководства компании оказывается поддержка в вопросах саморазвития и самосовершенствования: курсы, семинары, выставки (российские и зарубежные).</p> <p><strong>Основные задачи:</strong></p> <p>- слесарно-сварочные работы.</p> <p><strong>Мы уже готовы работать с Вами, если Вы:</strong></p> <p>- имеете среднее/высшее образование;</p> <p>- постоянно стремитесь к саморазвитию;</p> <p>- активный, позитивный и нацеленный на результат.</p> <p><strong>Мы гарантируем:</strong></p> <p>- прозрачную систему мотивации: оклад + КЭК;</p> <p>- средний уровень дохода 70 000 – 80 000 руб.;</p> <p>- выплата заработной платы 2 раза в месяц без задержек;</p> <p>- оплачиваемый отпуск 2 раза в год;</p> <p>- график работы 5/2, пн-пт, c 9:00 до 18:00;</p> <p>- оформление по ТК РФ;</p> <p>- возможность карьерного и зарплатного роста;</p> <p>- выстроенная система обучения и наставничества (за сотрудником на этапе испытательного срока закрепляется наставник; обучение проходит по разработанной методике с применением различных средств визуализации материала);</p> <p>- работа с продуктом premium класса;</p> <p>- статус мирового бренда (мировое имя, статус и узнаваемость; продукт продаёт сам себя);</p> <p>- насыщенная корпоративная жизнь: мероприятия, направленные на сплочение команды и совместное преодоление трудностей. Пример: сплав по Хопру в июле 2023 г.;</p> <p>- спортивные мероприятия: игры (волейбол, большой теннис), праздники спортивной направленности - &quot;Мама, папа, Я - спортивная семья&quot;;</p> <p>- культурные мероприятия: совместное посещение выставок, организация экскурсионных поездок, проведение выставок - продаж изделий ручной работы сотрудников (&quot;Выставка мастеров Sagarti&quot;);</p> <p>- корпоративная библиотека, включающая большое количество литературы (жанры: бизнес-стратегии; зарубежная деловая литература; креатив / идеи; искусство: живопись, скульптура, графика, дпи; саморазвитие; психология; автобиография);</p> <p>- компания оплачивает доп. обучение сотрудников после испытательного срока;</p> <p>- адекватный и вовлеченный руководитель в процесс развития компании и каждого сотрудника;</p> <p>- стиль ведения бизнеса - руководитель компании учитывает тренды делового мира и подходящее для компании применяет на практике (он постоянно совершенствуется в профессиональной сфере (идёт в ногу со временем) и использует полученные знания на практике, исходя из особенностей компании);</p> <p>- психологическая безопасность (обстановка в коллективе, которая позволяет сотрудникам действовать, не опасаясь негативных последствий, связанных с самооценкой, статусом или карьерой);</p> <p>- информирование сотрудников (корпоративные информационные площадки - каналы с разбивкой по направлениям: &quot;Болталка&quot;, &quot;Активности&quot;, &quot;Новости&quot;, &quot;Объявления&quot;, &quot;Контент (фото и видео)&quot; , &quot;Образование&quot;, &quot;Идеи и предложения&quot;, &quot;Показатели успеха&quot;);</p> <p>- сбор обратной связи со всех сотрудников (проведение различных опросов с возможностью остаться анонимом);</p> <p>- многие предложения сотрудников учитываются и воплощаются в жизнь (наши сотрудники стремятся реализовать свои идеи на практике, озвучивают свои видения, а собственник компании поддерживает и даёт возможность для воплощения);</p> <p>- подарки к праздникам (НГ, 23 февраля, 8 марта);</p> <p>- выделение денежных средств сотрудникам по случаю значимых жизненных событий (выделение матпомощи).</p> <p><strong><em>Если Вы ищете для себя площадку, на которой не только можно реализовать свой потенциал, но и постоянно развивать профессиональный уровень, то окликайтесь на вакансию!</em></strong></p> <p><em>Ждём Ваших резюме!</em></p> <p><em><strong>Внимание! Вакансия открыта до 31.03</strong>.</em></p>","branded_description":null,"vacancy_constructor_template":null,"key_skills":[{"name":"Сварочные работы"},{"name":"Обучение и развитие"}],"accept_handicapped":false,"accept_kids":false,"archived":false,"response_url":null,"specializations":[],"professional_roles":[{"id":"109","name":"Сварщик"}],"code":null,"hidden":false,"quick_responses_allowed":false,"driver_license_types":[],"accept_incomplete_resumes":true,"employer":{"id":"2199532","name":"Sagarti","url":"https://api.hh.ru/employers/2199532?host=hh.ru","alternate_url":"https://hh.ru/employer/2199532","logo_urls":{"240":"https://img.hhcdn.ru/employer-logo/6077590.jpeg","90":"https://img.hhcdn.ru/employer-logo/6077589.jpeg","original":"https://img.hhcdn.ru/employer-logo-original/1114248.jpg"},"vacancies_url":"https://api.hh.ru/vacancies?employer_id=2199532&host=hh.ru","accredited_it_employer":false,"trusted":true},"published_at":"2024-03-14T00:26:57+0300","created_at":"2024-03-14T00:26:57+0300","initial_created_at":"2024-03-14T00:26:57+0300","negotiations_url":null,"suitable_resumes_url":null,"apply_alternate_url":"https://hh.ru/applicant/vacancy_response?vacancyId=94722129","has_test":false,"test":null,"alternate_url":"https://hh.ru/vacancy/94722129","working_days":[],"working_time_intervals":[],"working_time_modes":[],"accept_temporary":false,"languages":[],"approved":true}